sonantic/__init__.py
sonantic/core.py
sonantic/logger.py
sonantic/py.typed
sonantic/serialiser.py
sonantic/speech.py
sonantic/version.py
sonantic/voices.py
sonantic-0.1.0.dist-info/LICENSE
sonantic-0.1.0.dist-info/METADATA
sonantic-0.1.0.dist-info/WHEEL
sonantic-0.1.0.dist-info/top_level.txt
sonantic-0.1.0.dist-info/RECORD
