Metadata-Version: 2.1
Name: sonantic
Version: 0.1.0
Summary: Python client for the Sonantic API
Home-page: https://github.com/sonantic-samples/sonantic-python
Author: Sonantic
Author-email: support@sonantic.io
License: MIT
Platform: UNKNOWN
Requires-Python: >=3.8
License-File: LICENSE
Requires-Dist: requests
Requires-Dist: pydantic
Provides-Extra: all
Requires-Dist: requests ; extra == 'all'
Requires-Dist: pydantic ; extra == 'all'
Requires-Dist: pytest ; extra == 'all'
Requires-Dist: black ; extra == 'all'
Requires-Dist: isort ; extra == 'all'
Requires-Dist: pre-commit ; extra == 'all'
Requires-Dist: build ; extra == 'all'
Requires-Dist: twine ; extra == 'all'
Provides-Extra: dev
Requires-Dist: black ; extra == 'dev'
Requires-Dist: isort ; extra == 'dev'
Requires-Dist: pre-commit ; extra == 'dev'
Requires-Dist: build ; extra == 'dev'
Requires-Dist: twine ; extra == 'dev'
Provides-Extra: test
Requires-Dist: pytest ; extra == 'test'
